advent-of-python/__init__.py
docs/source/conf.py
advent_of_python-0.0.1.dist-info/METADATA
advent_of_python-0.0.1.dist-info/WHEEL
advent_of_python-0.0.1.dist-info/licenses/LICENSE
advent_of_python-0.0.1.dist-info/RECORD
